[{"_id":"65559364b6454146f18ed74c","name":"Party Mix","songs":["song_id_1","song_id_5","song_id_10","song_id_15"],"timeslot":"10:00pm"},{"_id":"65559364b6454146f18ed74d","name":"Chill Vibes","songs":["song_id_2","song_id_6","song_id_11","song_id_16"],"timeslot":"12:00pm"},{"_id":"65559364b6454146f18ed74e","name":"Workout Beats","songs":["song_id_3","song_id_7","song_id_12","song_id_17"],"timeslot":"11:00pm"},{"_id":"65559364b6454146f18ed74f","name":"Road Trip Jams","songs":["song_id_4","song_id_8","song_id_13","song_id_18"],"timeslot":"11:00pm"},{"_id":"65559364b6454146f18ed750","name":"Relaxing Evening","songs":["song_id_9","song_id_14","song_id_19","song_id_20"],"timeslot":"11:00pm"},{"_id":"65559364b6454146f18ed751","name":"Throwback Hits","songs":["song_id_1","song_id_6","song_id_11","song_id_16"],"timeslot":"12:00pm"},{"_id":"65559364b6454146f18ed752","name":"Top 20","songs":["song_id_2","song_id_7","song_id_12","song_id_17"],"timeslot":"12:00pm"},{"_id":"65559364b6454146f18ed753","name":"Study Session","songs":["song_id_3","song_id_8","song_id_13","song_id_18"],"timeslot":"10:00pm"},{"_id":"65559364b6454146f18ed754","name":"Weekend Vibes","songs":["song_id_4","song_id_9","song_id_14","song_id_19"],"timeslot":"11:00pm"},{"_id":"65559364b6454146f18ed755","name":"Feel Good Mix","songs":["song_id_5","song_id_10","song_id_15","song_id_20"],"timeslot":"10:00pm"},{"name":"hi","songs":[],"timeslot":"9:00pm","_id":"6568731dd1faa064ae4ffd10"},{"name":"Rap","songs":["song_id_1","song_id_8","song_id_11","song_id_19"],"timeslot":"12:00pm","_id":"65687d9bdb0f2fa217c7d0e7"},{"name":"Rap","songs":["song_id_1","song_id_5"],"timeslot":"9:00pm","_id":"65688d16d1c6b6f5eec64275"},{"name":"Rap","songs":["song_id_1","song_id_6","song_id_13","song_id_2"],"timeslot":"01:00pm","_id":"65689bfc2b09a2c27f071810"},{"name":"Rap","songs":["song_id_15","song_id_11","song_id_12","song_id_8"],"timeslot":"11:00pm","_id":"65689d9f4a9a3d04d4fe0d60"}]